jsonschema_diff/__init__.py
jsonschema_diff/cli.py
jsonschema_diff/config_maker.py
jsonschema_diff/py.typed
jsonschema_diff/pypi_interface.py
jsonschema_diff/table_render.py
jsonschema_diff/color/__init__.py
jsonschema_diff/color/abstraction.py
jsonschema_diff/color/base.py
jsonschema_diff/color/stages/__init__.py
jsonschema_diff/color/stages/mono_lines.py
jsonschema_diff/color/stages/path.py
jsonschema_diff/color/stages/replace.py
jsonschema_diff/core/__init__.py
jsonschema_diff/core/abstraction.py
jsonschema_diff/core/compare_base.py
jsonschema_diff/core/compare_combined.py
jsonschema_diff/core/config.py
jsonschema_diff/core/property.py
jsonschema_diff/core/custom_compare/__init__.py
jsonschema_diff/core/custom_compare/list.py
jsonschema_diff/core/custom_compare/range.py
jsonschema_diff/core/tools/__init__.py
jsonschema_diff/core/tools/combine.py
jsonschema_diff/core/tools/compare.py
jsonschema_diff/core/tools/context.py
jsonschema_diff/core/tools/render.py
jsonschema_diff/sphinx/__init__.py
jsonschema_diff/sphinx/directive.py
jsonschema_diff-0.1.7.dist-info/licenses/LICENSE
jsonschema_diff-0.1.7.dist-info/METADATA
jsonschema_diff-0.1.7.dist-info/WHEEL
jsonschema_diff-0.1.7.dist-info/entry_points.txt
jsonschema_diff-0.1.7.dist-info/top_level.txt
jsonschema_diff-0.1.7.dist-info/RECORD
