Metadata-Version: 2.4
Name: jsonschema-diff
Version: 0.1.7
Summary: A library for comparing JSON schemas and displaying differences
Author-email: Miskler <mail@miskler.ru>
License: MIT License
Project-URL: Homepage, https://github.com/Miskler/jsonschema-diff
Project-URL: Repository, https://github.com/Miskler/jsonschema-diff
Project-URL: Documentation, https://miskler.github.io/jsonschema-diff/basic/quick_start/index.html
Project-URL: Issues, https://github.com/Miskler/jsonschema-diff/issues
Keywords: json,schema,diff,comparison
Classifier: Development Status :: 4 - Beta
Classifier: Intended Audience :: Developers
Classifier: License :: OSI Approved :: MIT License
Classifier: Operating System :: OS Independent
Classifier: Programming Language :: Python :: 3
Classifier: Programming Language :: Python :: 3.10
Classifier: Programming Language :: Python :: 3.11
Classifier: Programming Language :: Python :: 3.12
Classifier: Programming Language :: Python :: 3.13
Classifier: Topic :: Software Development :: Libraries :: Python Modules
Classifier: Topic :: Utilities
Requires-Python: >=3.10
License-File: LICENSE
Requires-Dist: rich
Provides-Extra: dev
Requires-Dist: pytest; extra == "dev"
Requires-Dist: pytest-cov; extra == "dev"
Requires-Dist: pytest-xdist; extra == "dev"
Requires-Dist: black; extra == "dev"
Requires-Dist: isort; extra == "dev"
Requires-Dist: mypy; extra == "dev"
Requires-Dist: flake8; extra == "dev"
Requires-Dist: sphinx; extra == "dev"
Requires-Dist: sphinx-autoapi; extra == "dev"
Requires-Dist: furo; extra == "dev"
Requires-Dist: docutils; extra == "dev"
Requires-Dist: types-docutils; extra == "dev"
Dynamic: license-file
